pushed_over/__init__.py
pushed_over/_types.py
pushed_over/main.py
pushed_over-0.1.3.dist-info/METADATA
pushed_over-0.1.3.dist-info/WHEEL
pushed_over-0.1.3.dist-info/top_level.txt
pushed_over-0.1.3.dist-info/RECORD
