Metadata-Version: 2.1
Name: pushed-over
Version: 0.1.3
Summary: Typed, async client for the Pushover API
Author-email: Marcel Claramunt <marcel@moveread.com>
Project-URL: repo, https://github.com/moveread/REPO.git
Requires-Python: >=3.10
Requires-Dist: pydantic
Requires-Dist: httpx
Requires-Dist: haskellian
